<?xml version="1.0" encoding="UTF-8"?>
<objects serializationModel="Studio.02.03.00">
	<object class="AudioFile" id="{59549449-3c83-4d98-834e-851831890e3e}">
		<property name="assetPath">
			<value>1 (153).mp3</value>
		</property>
		<property name="frequencyInKHz">
			<value>44.0999985</value>
		</property>
		<property name="channelCount">
			<value>2</value>
		</property>
		<property name="length">
			<value>3.5004081632653059</value>
		</property>
		<relationship name="masterAssetFolder">
			<destination>{06989a4d-a27a-48e6-86f1-116b6b9f3f01}</destination>
		</relationship>
	</object>
</objects>
